streamledge/__init__.py
streamledge/__main__.py
streamledge/config_utils.py
streamledge/main.py
streamledge-0.1.0.dist-info/licenses/LICENSE
streamledge_server/__init__.py
streamledge_server/__main__.py
streamledge_server/main.py
streamledge_server/static/icons/kick.ico
streamledge_server/static/icons/twitch.ico
streamledge_server/static/icons/youtube.ico
streamledge_server/templates/play_video.html
streamledge_server/templates/play_youtube.html
streamledge_server/templates/twitch_chat.html
streamledge-0.1.0.dist-info/METADATA
streamledge-0.1.0.dist-info/WHEEL
streamledge-0.1.0.dist-info/entry_points.txt
streamledge-0.1.0.dist-info/top_level.txt
streamledge-0.1.0.dist-info/RECORD
