Metadata-Version: 2.4
Name: streamledge
Version: 0.1.0
Summary: A command line YouTube and Twitch.tv player
Author: Blasman
License: MIT
Project-URL: Homepage, https://github.com/Blasman/Streamledge
Project-URL: Source, https://github.com/Blasman/Streamledge
Keywords: youtube,twitch,cli,player,stream,video,kick
Classifier: Programming Language :: Python :: 3
Classifier: Programming Language :: Python :: 3.9
Classifier: Programming Language :: Python :: 3.10
Classifier: Programming Language :: Python :: 3.11
Classifier: Programming Language :: Python :: 3.12
Classifier: License :: OSI Approved :: MIT License
Classifier: Operating System :: OS Independent
Classifier: Environment :: Console
Classifier: Intended Audience :: End Users/Desktop
Classifier: Topic :: Multimedia :: Video
Classifier: Topic :: Utilities
Requires-Python: >=3.9
License-File: LICENSE
Requires-Dist: platformdirs==4.4.0
Requires-Dist: Flask==3.1.1
Requires-Dist: curl-cffi==0.12.0
Dynamic: license-file
